odoo9_addon_l10n_ch_base_bank-9.0.1.1.1-py2.7-nspkg.pth
odoo_addons/l10n_ch_base_bank/__openerp__.py
odoo_addons/l10n_ch_base_bank/__init__.py
odoo_addons/l10n_ch_base_bank/README.rst
odoo_addons/l10n_ch_base_bank/models/bank.py
odoo_addons/l10n_ch_base_bank/models/__init__.py
odoo_addons/l10n_ch_base_bank/models/invoice.py
odoo_addons/l10n_ch_base_bank/i18n/ja.po
odoo_addons/l10n_ch_base_bank/i18n/zh_CN.po
odoo_addons/l10n_ch_base_bank/i18n/nb_NO.po
odoo_addons/l10n_ch_base_bank/i18n/tr_TR.po
odoo_addons/l10n_ch_base_bank/i18n/ru.po
odoo_addons/l10n_ch_base_bank/i18n/pt.po
odoo_addons/l10n_ch_base_bank/i18n/fr_CH.po
odoo_addons/l10n_ch_base_bank/i18n/it.po
odoo_addons/l10n_ch_base_bank/i18n/es.po
odoo_addons/l10n_ch_base_bank/i18n/nl_BE.po
odoo_addons/l10n_ch_base_bank/i18n/ar.po
odoo_addons/l10n_ch_base_bank/i18n/lt.po
odoo_addons/l10n_ch_base_bank/i18n/ro.po
odoo_addons/l10n_ch_base_bank/i18n/tr.po
odoo_addons/l10n_ch_base_bank/i18n/mk.po
odoo_addons/l10n_ch_base_bank/i18n/hr.po
odoo_addons/l10n_ch_base_bank/i18n/bg.po
odoo_addons/l10n_ch_base_bank/i18n/es_EC.po
odoo_addons/l10n_ch_base_bank/i18n/zh_TW.po
odoo_addons/l10n_ch_base_bank/i18n/gl.po
odoo_addons/l10n_ch_base_bank/i18n/l10n_ch_base_bank.pot
odoo_addons/l10n_ch_base_bank/i18n/ca.po
odoo_addons/l10n_ch_base_bank/i18n/id.po
odoo_addons/l10n_ch_base_bank/i18n/es_CR.po
odoo_addons/l10n_ch_base_bank/i18n/sl.po
odoo_addons/l10n_ch_base_bank/i18n/th.po
odoo_addons/l10n_ch_base_bank/i18n/cs.po
odoo_addons/l10n_ch_base_bank/i18n/pt_PT.po
odoo_addons/l10n_ch_base_bank/i18n/eu.po
odoo_addons/l10n_ch_base_bank/i18n/sk_SK.po
odoo_addons/l10n_ch_base_bank/i18n/et.po
odoo_addons/l10n_ch_base_bank/i18n/mn.po
odoo_addons/l10n_ch_base_bank/i18n/nl.po
odoo_addons/l10n_ch_base_bank/i18n/de.po
odoo_addons/l10n_ch_base_bank/i18n/fr.po
odoo_addons/l10n_ch_base_bank/i18n/pl.po
odoo_addons/l10n_ch_base_bank/i18n/bs.po
odoo_addons/l10n_ch_base_bank/i18n/pt_BR.po
odoo9_addon_l10n_ch_base_bank-9.0.1.1.1.dist-info/top_level.txt
odoo9_addon_l10n_ch_base_bank-9.0.1.1.1.dist-info/WHEEL
odoo9_addon_l10n_ch_base_bank-9.0.1.1.1.dist-info/RECORD
odoo9_addon_l10n_ch_base_bank-9.0.1.1.1.dist-info/metadata.json
odoo9_addon_l10n_ch_base_bank-9.0.1.1.1.dist-info/DESCRIPTION.rst
odoo9_addon_l10n_ch_base_bank-9.0.1.1.1.dist-info/METADATA
odoo9_addon_l10n_ch_base_bank-9.0.1.1.1.dist-info/namespace_packages.txt
