Metadata-Version: 2.0
Name: odoo9-addon-l10n-ch-base-bank
Version: 9.0.1.1.1
Summary: Types and number validation for swiss electronic pmnt. DTA, ESR
Home-page: http://www.camptocamp.com
Author: Camptocamp,Odoo Community Association (OCA)
Author-email: support@odoo-community.org
License: AGPL-3
Platform: UNKNOWN
Requires-Dist: odoo (<9.1a,>=9.0a)
Requires-Dist: odoo9-addon-account-payment-partner
Classifier: Programming Language :: Python :: 2.7
Classifier: Framework :: Odoo
Classifier: License :: OSI Approved :: GNU Affero General Public License v3
